{
  "pokemon": [
    {
      "uniqueID": 0,
      "id": "3",
      "nickname": "venusaur",
      "renameStatus": 0
    },
    {
      "uniqueID": 1,
      "id": "3",
      "nickname": "Richard",
      "renameStatus": 0
    },
    {
      "uniqueID": 1,
      "id": "8",
      "nickname": "Richard",
      "renameStatus": 0
    },
    {
      "uniqueID": 1,
      "id": "49",
      "nickname": "Richard",
      "renameStatus": 0
    },
    {
      "uniqueID": 3,
      "id": "10",
      "nickname": "Wahyu",
      "renameStatus": 0
    },
    {
      "uniqueID": 1,
      "id": "6",
      "nickname": "Richard",
      "renameStatus": 0
    }
  ]
}